peoplesoft_components/__init__.py
peoplesoft_components/abstract_clickable_component.py
peoplesoft_components/abstract_input_component.py
peoplesoft_components/base_component.py
peoplesoft_components/button.py
peoplesoft_components/checkbox.py
peoplesoft_components/components.json
peoplesoft_components/dropdown_button.py
peoplesoft_components/image.py
peoplesoft_components/json_locators.py
peoplesoft_components/link.py
peoplesoft_components/lookup_text_input.py
peoplesoft_components/nav_bar.py
peoplesoft_components/password_input.py
peoplesoft_components/select.py
peoplesoft_components/table.py
peoplesoft_components/text.py
peoplesoft_components/text_input.py
peoplesoft_components/tile.py
peoplesoft_components/toggle_switch.py
peoplesoft_pages/__init__.py
peoplesoft_pages/base_fluid_page.py
peoplesoft_pages/base_page.py
peoplesoft_selenium_components-0.3.2.dist-info/LICENSE.md
peoplesoft_selenium_components-0.3.2.dist-info/METADATA
peoplesoft_selenium_components-0.3.2.dist-info/WHEEL
peoplesoft_selenium_components-0.3.2.dist-info/RECORD
