Metadata-Version: 2.3
Name: peoplesoft-selenium-components
Version: 0.3.2
Summary: A helpful library for finding and interacting with PeopleSoft components using Selenium
License: MIT
Author: jsa34
Author-email: jsa34@cam.ac.uk
Requires-Python: >=3.10
Classifier: License :: OSI Approved :: MIT License
Classifier: Programming Language :: Python :: 3
Classifier: Programming Language :: Python :: 3.10
Classifier: Programming Language :: Python :: 3.11
Classifier: Programming Language :: Python :: 3.12
Classifier: Programming Language :: Python :: 3.13
Requires-Dist: selenium (>=4)
Requires-Dist: selocity
